keaton_verysimplemodule/__init__.py
keaton_verysimplemodule/add.py
keaton_verysimplemodule/subtract.py
keaton_verysimplemodule/extras/__init__.py
keaton_verysimplemodule/extras/divide.py
keaton_verysimplemodule/extras/multiply.py
verysimplemodule/__init__.py
verysimplemodule/add.py
verysimplemodule/subtract.py
verysimplemodule/extras/__init__.py
verysimplemodule/extras/divide.py
verysimplemodule/extras/multiply.py
keaton_verysimplemodule-0.0.1.dist-info/METADATA
keaton_verysimplemodule-0.0.1.dist-info/WHEEL
keaton_verysimplemodule-0.0.1.dist-info/top_level.txt
keaton_verysimplemodule-0.0.1.dist-info/RECORD
